[
  {
    "id": "Ajjat",
    "subtitle": "Skill Master",
    "category": "npc",
    "sortingGroups": ["attack", "melee"],
    "requiredLevel": 99,
    "notableDrops": [
      "Attack_hood",
      "Attack_cape",
      "Attack_cape(t)"
    ]
  },
  {
    "id": "Alwyn",
    "subtitle": "Estate Agent",
    "category": "npc",
    "sortingGroups": ["construction"],
    "notableDrops": [
      "Construct._hood",
      "Construct._cape",
      "Construct._cape(t)"
    ]
  },
  {
    "id": "Armour_salesman",
    "title": "Aaron",
    "subtitle": "Skill Master",
    "category": "npc",
    "sortingGroups": ["ranged"],
    "requiredLevel": 99,
    "notableDrops": [
      "Ranging_hood",
      "Ranging_cape",
      "Ranging_cape(t)"
    ]
  },
  {
    "id": "Aubury",
    "subtitle": "Skill Master",
    "category": "npc",
    "sortingGroups": ["runecraft"],
    "requiredLevel": 99,
    "notableDrops": [
      "Runecraft_hood",
      "Runecraft_cape",
      "Runecraft_cape(t)"
    ]
  },
  {
    "id": "Bob_Barter_(herbs)",
    "title": "Bob Barter",
    "subtitle": "Decanting",
    "category": "npc",
    "sortingGroups": ["herblore"]
  },
  {
    "id": "Brother_Jered",
    "subtitle": "Skill Master",
    "category": "npc",
    "sortingGroups": ["prayer"],
    "requiredLevel": 99,
    "notableDrops": [
      "Prayer_hood",
      "Prayer_cape",
      "Prayer_cape(t)"
    ]
  },
  {
    "id": "Cap'n_Izzy_No-Beard",
    "subtitle": "Skill Master",
    "category": "npc",
    "sortingGroups": ["agility"],
    "requiredLevel": 99,
    "notableDrops": [
      "Agility_hood",
      "Agility_cape",
      "Agility_cape(t)"
    ]
  },
  {
    "id": "Chaeldar",
    "subtitle": "Slayer Master",
    "category": "npc",
    "sortingGroups": ["slayer"]
  },
  {
    "id": "Duradel",
    "subtitle": "Slayer Master",
    "category": "npc",
    "sortingGroups": ["slayer"],
    "requiredLevel": 99,
    "notableDrops": [
      "Slayer_hood",
      "Slayer_cape",
      "Slayer_cape(t)"
    ]
  },
  {
    "id": "Ellis",
    "title": "Tanner",
    "subtitle": "Al Kharid",
    "category": "npc",
    "sortingGroups": ["crafting"],
    "notableDrops": [
      "Leather",
      "Hard_leather",
      "Snakeskin",
      "Green_dragon_leather",
      "Blue_dragon_leather",
      "Red_dragon_leather",
      "Black_dragon_leather"
    ]
  },
  {
    "id": "Eodan",
    "title": "Tanner",
    "subtitle": "Forthos Dungeon",
    "category": "npc",
    "sortingGroups": ["crafting"],
    "notableDrops": [
      "Leather",
      "Hard_leather",
      "Snakeskin",
      "Green_dragon_leather",
      "Blue_dragon_leather",
      "Red_dragon_leather",
      "Black_dragon_leather"
    ]
  },
  {
    "id": "Estate_agent",
    "category": "npc",
    "sortingGroups": ["construction"],
    "notableDrops": [
      "Construct._hood",
      "Construct._cape",
      "Construct._cape(t)"
    ]
  },
  {
    "id": "Friendly_Forester",
    "subtitle": "NPC",
    "category": "npc",
    "sortingGroups": ["woodcutting"],
    "notableDrops": [
      "Forestry_kit",
      "Log_brace",
      "Clothes_pouch_blueprint",
      "Cape_pouch",
      "Log_basket",
      "Felling_axe_handle",
      "Funky_shaped_log",
      "Forestry_hat",
      "Forestry_top",
      "Forestry_legs",
      "Forestry_boots",
      "Twitcher's_gloves"
    ]
  },
  {
    "id": "Gadrin",
    "subtitle": "Skill Master",
    "category": "npc",
    "sortingGroups": ["mining"],
    "requiredLevel": 99,
    "notableDrops": [
      "Mining_hood",
      "Mining_cape",
      "Mining_cape(t)"
    ]
  },
  {
    "id": "Ghommal",
    "icon": "Ghommal's_lucky_penny",
    "subtitle": "Combat Achievements",
    "category": "npc",
    "sortingGroups": ["pvm"],
    "notableDrops": [
      "Ghommal's_hilt_1",
      "Ghommal's_hilt_2",
      "Ghommal's_hilt_3",
      "Ghommal's_hilt_4",
      "Ghommal's_hilt_5",
      "Ghommal's_hilt_6",
      "#newline",
      "Ghommal's_lucky_penny",
      "Tztok_slayer_helmet",
      "Vampyric_slayer_helmet",
      "Tzkal_slayer_helmet"
    ]
  },
  {
    "id": "Grace",
    "subtitle": "NPC",
    "category": "npc",
    "sortingGroups": ["agility", "herblore"],
    "notableDrops": [
      "Graceful_hood",
      "Graceful_top",
      "Graceful_legs",
      "Graceful_gloves",
      "Graceful_boots",
      "Graceful_cape",
      "Amylase_pack"
    ]
  },
  {
    "id": "Harlan",
    "subtitle": "Skill Master",
    "category": "npc",
    "sortingGroups": ["defence", "melee"],
    "requiredLevel": 99,
    "notableDrops": [
      "Defence_hood",
      "Defence_cape",
      "Defence_cape(t)"
    ]
  },
  {
    "id": "Head_chef",
    "subtitle": "Skill Master",
    "category": "npc",
    "sortingGroups": ["cooking"],
    "requiredLevel": 99,
    "notableDrops": [
      "Cooking_hood",
      "Cooking_cape",
      "Cooking_cape(t)"
    ]
  },
  {
    "id": "Hickton",
    "subtitle": "Skill Master",
    "category": "npc",
    "sortingGroups": ["fletching"],
    "requiredLevel": 99,
    "notableDrops": [
      "Fletching_hood",
      "Fletching_cape",
      "Fletching_cape(t)"
    ]
  },
  {
    "id": "Hunting_expert",
    "subtitle": "Skill Master",
    "category": "npc",
    "sortingGroups": ["hunter"],
    "requiredLevel": 99,
    "notableDrops": [
      "Hunter_hood",
      "Hunter_cape",
      "Hunter_cape(t)"
    ]
  },
  {
    "id": "Ignatius_Vulcan",
    "subtitle": "Skill Master",
    "category": "npc",
    "sortingGroups": ["firemaking"],
    "requiredLevel": 99,
    "notableDrops": [
      "Firemaking_hood",
      "Firemaking_cape",
      "Firemaking_cape(t)"
    ]
  },
  {
    "id": "Kaqemeex",
    "subtitle": "Skill Master",
    "category": "npc",
    "sortingGroups": ["herblore"],
    "requiredLevel": 99,
    "notableDrops": [
      "Herblore_hood",
      "Herblore_cape",
      "Herblore_cape(t)"
    ]
  },
  {
    "id": "Konar",
    "subtitle": "Slayer Master",
    "category": "npc",
    "sortingGroups": ["slayer"]
  },
  {
    "id": "Krystilia",
    "subtitle": "Slayer Master",
    "category": "npc",
    "sortingGroups": ["slayer"]
  },
  {
    "id": "Leatherworker",
    "title": "Tanner",
    "subtitle": "Ranging Guild",
    "category": "npc",
    "sortingGroups": ["crafting"],
    "notableDrops": [
      "Leather",
      "Hard_leather",
      "Snakeskin",
      "Green_dragon_leather",
      "Blue_dragon_leather",
      "Red_dragon_leather",
      "Black_dragon_leather"
    ]
  },
  {
    "id": "Mac",
    "icon": "Stats_icon",
    "subtitle": "Skill Master",
    "category": "npc",
    "sortingGroups": ["misc"],
    "notableDrops": [
      "Max_hood",
      "Max_cape"
    ]
  },
  {
    "id": "Magic_combat_tutor",
    "category": "npc",
    "sortingGroups": ["magic"],
    "notableDrops": [
      "Air_rune",
      "Mind_rune"
    ]
  },
  {
    "id": "Martin_the_Master_Gardener",
    "title": "Martin",
    "subtitle": "Master Farmer",
    "category": "npc",
    "sortingGroups": ["farming", "thieving"],
    "requiredLevel": 99,
    "notableDrops": [
      "Farming_hood",
      "Farming_cape",
      "Farming_cape(t)"
    ]
  },
  {
    "id": "Martin_Thwait",
    "subtitle": "Skill Master",
    "category": "npc",
    "sortingGroups": ["thieving"],
    "requiredLevel": 99,
    "notableDrops": [
      "Thieving_hood",
      "Thieving_cape",
      "Thieving_cape(t)"
    ]
  },
  {
    "id": "Mary_(Getting_Ahead)",
    "title": "Tanner",
    "subtitle": "Kebos Lowlands",
    "category": "npc",
    "sortingGroups": ["crafting"],
    "notableDrops": [
      "Leather",
      "Hard_leather",
      "Snakeskin",
      "Green_dragon_leather",
      "Blue_dragon_leather",
      "Red_dragon_leather",
      "Black_dragon_leather"
    ]
  },
  {
    "id": "Master_crafter",
    "subtitle": "Crafting Guild",
    "category": "npc",
    "sortingGroups": ["crafting"],
    "requiredLevel": 99,
    "notableDrops": [
      "Crafting_hood",
      "Crafting_cape",
      "Crafting_cape(t)"
    ]
  },
  {
    "id": "Master_fisher",
    "subtitle": "Fishing Guild",
    "category": "npc",
    "sortingGroups": ["fishing"],
    "requiredLevel": 99,
    "notableDrops": [
      "Fishing_hood",
      "Fishing_cape",
      "Fishing_cape(t)"
    ]
  },
  {
    "id": "Mazchna",
    "subtitle": "Slayer Master",
    "category": "npc",
    "sortingGroups": ["slayer"]
  },
  {
    "id": "Melee_combat_tutor",
    "category": "npc",
    "sortingGroups": ["melee"],
    "notableDrops": [
      "Training_sword",
      "Training_shield"
    ]
  },
  {
    "id": "Metla",
    "subtitle": "NPC",
    "category": "npc",
    "sortingGroups": ["construction"],
    "notableDrops": [
      "Limestone_brick",
      "Marble_block",
      "Gold_leaf",
      "Magic_stone",
      "Condensed_gold"
    ]
  },
  {
    "id": "Nieve",
    "subtitle": "Slayer Master",
    "category": "npc",
    "sortingGroups": ["slayer"]
  },
  {
    "id": "Olaf_the_Bard",
    "icon": "Music",
    "category": "npc",
    "sortingGroups": ["misc", "music"],
    "notableDrops": [
      "Music_hood",
      "Music_cape",
      "Music_cape(t)"
    ]
  },
  {
    "id": "Ranged_combat_tutor",
    "category": "npc",
    "sortingGroups": ["ranged"],
    "notableDrops": [
      "Training_bow",
      "Training_arrows"
    ]
  },
  {
    "id": "Sbott",
    "title": "Tanner",
    "subtitle": "Canifis",
    "category": "npc",
    "sortingGroups": ["crafting"],
    "notableDrops": [
      "Leather",
      "Hard_leather",
      "Snakeskin",
      "Green_dragon_leather",
      "Blue_dragon_leather",
      "Red_dragon_leather",
      "Black_dragon_leather"
    ]
  },
  {
    "id": "Sloane",
    "subtitle": "Skill Master",
    "category": "npc",
    "sortingGroups": ["strength", "melee"],
    "requiredLevel": 99,
    "notableDrops": [
      "Strength_hood",
      "Strength_cape",
      "Strength_cape(t)"
    ]
  },
  {
    "id": "Spria",
    "subtitle": "Slayer Master",
    "category": "npc",
    "sortingGroups": ["slayer"]
  },
  {
    "id": "Stonemason",
    "subtitle": "NPC",
    "category": "npc",
    "sortingGroups": ["construction"],
    "notableDrops": [
      "Limestone_brick",
      "Marble_block",
      "Magic_stone",
      "Gold_leaf",
      "Condensed_gold"
    ]
  },
  {
    "id": "Surgeon_General_Tafani",
    "subtitle": "Skill Master",
    "category": "npc",
    "sortingGroups": ["hitpoints"],
    "requiredLevel": 99,
    "notableDrops": [
      "Hitpoints_hood",
      "Hitpoints_cape",
      "Hitpoints_cape(t)"
    ]
  },
  {
    "id": "Tanner_(Crafting_Guild)",
    "title": "Tanner",
    "subtitle": "Crafting Guild",
    "category": "npc",
    "sortingGroups": ["crafting"],
    "notableDrops": [
      "Leather",
      "Hard_leather",
      "Snakeskin",
      "Green_dragon_leather",
      "Blue_dragon_leather",
      "Red_dragon_leather",
      "Black_dragon_leather"
    ]
  },
  {
    "id": "Thurgo",
    "subtitle": "Skill Master",
    "category": "npc",
    "sortingGroups": ["smithing"],
    "requiredLevel": 99,
    "notableDrops": [
      "Smithing_hood",
      "Smithing_cape",
      "Smithing_cape(t)"
    ]
  },
  {
    "id": "Turael",
    "subtitle": "Slayer Master",
    "category": "npc",
    "sortingGroups": ["slayer"]
  },
  {
    "id": "Twiggy_O'Korn",
    "icon": "Achievement_Diaries_icon",
    "category": "npc",
    "sortingGroups": ["misc", "diaries"],
    "notableDrops": [
      "Achievement_diary_hood",
      "Achievement_diary_cape",
      "Achievement_diary_cape_(t)"
    ]
  },
  {
    "id": "Vannaka",
    "subtitle": "Slayer Master",
    "category": "npc",
    "sortingGroups": ["slayer"]
  },
  {
    "id": "Wesley",
    "subtitle": "Crushing",
    "category": "npc",
    "sortingGroups": ["herblore"]
  },
  {
    "id": "Wise_Old_Man",
    "icon": "Quest_point_icon",
    "category": "npc",
    "sortingGroups": ["misc", "quest"],
    "notableDrops": [
      "Quest_point_hood",
      "Quest_point_cape",
      "Quest_point_cape_(t)"
    ]
  },
  {
    "id": "Wizard_Sinina",
    "subtitle": "Skill Master",
    "category": "npc",
    "sortingGroups": ["magic"],
    "requiredLevel": 99,
    "notableDrops": [
      "Magic_hood",
      "Magic_cape",
      "Magic_cape(t)"
    ]
  },
  {
    "id": "Woodsman_tutor",
    "title": "Wilfred",
    "subtitle": "Skill Master",
    "category": "npc",
    "sortingGroups": ["woodcutting"],
    "requiredLevel": 99,
    "notableDrops": [
      "Woodcutting_hood",
      "Woodcutting_cape",
      "Woodcut._cape(t)"
    ]
  },
  {
    "id": "Zahur",
    "subtitle": "Herbalist",
    "category": "npc",
    "sortingGroups": ["herblore"]
  }
]
